patron_Nizar_expoFP/__init__.py
patron_Nizar_expoFP/patron_Nizar_expoFP.py
patron_Nizar_expoFP-0.1.dist-info/METADATA
patron_Nizar_expoFP-0.1.dist-info/WHEEL
patron_Nizar_expoFP-0.1.dist-info/top_level.txt
patron_Nizar_expoFP-0.1.dist-info/RECORD
