Metadata-Version: 2.1
Name: patron-Nizar-expoFP
Version: 0.1
Summary: patron animado
Home-page: 
Author: Nombre del autor
Author-email: sm23.nkazze@iessantamariadeivissa.com
